LICENSE.txt
MANIFEST.in
readme.md
readme_pypi.md
requirements.txt
setup.py
BO4ML.egg-info/PKG-INFO
BO4ML.egg-info/SOURCES.txt
BO4ML.egg-info/dependency_links.txt
BO4ML.egg-info/requires.txt
BO4ML.egg-info/top_level.txt
BanditOpt/BO4ML.py
BanditOpt/ConditionalSpace.py
BanditOpt/ConfigSpace.py
BanditOpt/Forbidden.py
BanditOpt/HyperParameter.py
BanditOpt/HyperoptConverter.py
BanditOpt/ParamRange.py
BanditOpt/__init__.py
Component/__init__.py
Component/mHyperopt/__init__.py
Component/mHyperopt/hyperopt.py