Metadata-Version: 2.1
Name: BO4ML
Version: 0.2
Summary: BO4ML: Bayesian Optimization library AutoML
Home-page: https://github.com/ECOLE-ITN/NguyenSSCI2021
Author: Duc Anh Nguyen
Author-email: d.a.nguyen@liacs.leidenuniv.nl
License: GPL-3.0 License
Keywords: AutoML optimization,Combination sampling,Bayesian Optimization
Platform: UNKNOWN
